{
  "trackers": [
    {
      "type": "unknown",
      "url": "https://o4508405260615680.ingest.de.sentry.io/api/4509599011045456/envelope/?sentry_version=7&sentry_key=c181c5ffa57482ea9a2140af63512f37&sentry_client=sentry.javascript.sveltekit%2F10.51.0"
    },
    {
      "type": "unknown",
      "url": "https://tally.so/widgets/embed.js"
    }
  ],
  "cookies": [
    {
      "name": "_pk_ses.211.37da",
      "value": "1",
      "domain": "dora.inclusion.gouv.fr",
      "path": "/",
      "expires": 1779014148,
      "size": 17,
      "httpOnly": false,
      "secure": false,
      "session": false,
      "sameSite": "Lax",
      "priority": "Medium",
      "sourceScheme": "Secure",
      "sameParty": false
    },
    {
      "name": "_pk_id.211.37da",
      "value": "1eeee90f5bbc571d.1779012349.",
      "domain": "dora.inclusion.gouv.fr",
      "path": "/",
      "expires": 1812967549,
      "size": 43,
      "httpOnly": false,
      "secure": false,
      "session": false,
      "sameSite": "Lax",
      "priority": "Medium",
      "sourceScheme": "Secure",
      "sameParty": false
    }
  ],
  "headers": {
    "content-encoding": "gzip",
    "content-security-policy": "child-src https://aide.dora.inclusion.gouv.fr/ https://metabase.dora.inclusion.gouv.fr https://tally.so https://tube.numerique.gouv.fr; default-src 'none'; frame-src 'self' https://metabase.dora.inclusion.gouv.fr https://cse.google.com https://syndicatedsearch.goog https://tally.so https://tube.numerique.gouv.fr; worker-src 'self' blob:; connect-src 'self' data: https://api.dora.inclusion.gouv.fr https://*.sentry.io https://api-adresse.data.gouv.fr/ https://openmaptiles.data.gouv.fr https://openmaptiles.geo.data.gouv.fr/ https://openmaptiles.github.io/osm-bright-gl-style/ https://matomo.inclusion.beta.gouv.fr https://api.collectivite.fr https://cse.google.com; font-src 'self'; img-src 'self' data: https://www.google.com http://clients1.google.com https://ssl.gstatic.com https://encrypted-tbn0.gstatic.com; script-src 'self' 'unsafe-inline' https://tally.so/widgets/embed.js https://matomo.inclusion.beta.gouv.fr https://cse.google.com https://www.google.com http://clients1.google.com http://cse.google.com/adsense/search/async-ads.js 'unsafe-eval'; style-src 'self' https://tally.so/widgets/embed.js 'unsafe-inline' https://www.google.com; base-uri 'self'",
    "content-type": "text/html",
    "date": "Sun, 17 May 2026 10:05:48 GMT",
    "etag": "W/\"pt9pd4\"",
    "link": "<./_app/immutable/assets/dist.DDB4wByE.css>; rel=\"preload\"; as=\"style\"; nopush, <./_app/immutable/assets/modal.CtLaZ_Zl.css>; rel=\"preload\"; as=\"style\"; nopush, <./_app/immutable/assets/radio-buttons-field.BPO31Znh.css>; rel=\"preload\"; as=\"style\"; nopush, <./_app/immutable/assets/0.DYvPiU9H.css>; rel=\"preload\"; as=\"style\"; nopush, <./_app/immutable/assets/checkbox-mark.DbCfWO4g.css>; rel=\"preload\"; as=\"style\"; nopush, <./_app/immutable/assets/select-field.SkmZkpFI.css>; rel=\"preload\"; as=\"style\"; nopush, <./_app/immutable/assets/select.CgRwkEJ7.css>; rel=\"preload\"; as=\"style\"; nopush, <./_app/immutable/assets/service-search.8xXoUeI9.css>; rel=\"preload\"; as=\"style\"; nopush, <./_app/immutable/assets/8.CMjignmX.css>; rel=\"preload\"; as=\"style\"; nopush, <./_app/immutable/entry/start.DgTrbVXj.js>; rel=\"modulepreload\"; nopush, <./_app/immutable/chunks/Cy39fm1R.js>; rel=\"modulepreload\"; nopush, <./_app/immutable/chunks/RKoTVosh.js>; rel=\"modulepreload\"; nopush, <./_app/immutable/chunks/Dx2aI44N.js>; rel=\"modulepreload\"; nopush, <./_app/immutable/chunks/vswTejlv.js>; rel=\"modulepreload\"; nopush, <./_app/immutable/chunks/DvAXvptS.js>; rel=\"modulepreload\"; nopush, <./_app/immutable/chunks/CEBGt2CV.js>; rel=\"modulepreload\"; nopush, <./_app/immutable/entry/app.zObIYsV4.js>; rel=\"modulepreload\"; nopush, <./_app/immutable/chunks/Dvq2VtAb.js>; rel=\"modulepreload\"; nopush, <./_app/immutable/chunks/BS4pk9A0.js>; rel=\"modulepreload\"; nopush, <./_app/immutable/chunks/D-hR3Yq7.js>; rel=\"modulepreload\"; nopush, <./_app/immutable/chunks/SF1ijtjI.js>; rel=\"modulepreload\"; nopush, <./_app/immutable/chunks/Bt33Xg87.js>; rel=\"modulepreload\"; nopush, <./_app/immutable/chunks/C5FeTJ8L.js>; rel=\"modulepreload\"; nopush, <./_app/immutable/chunks/um_34XaI.js>; rel=\"modulepreload\"; nopush, <./_app/immutable/chunks/Dv6-3chq.js>; rel=\"modulepreload\"; nopush, <./_app/immutable/chunks/Bol1eLPc.js>; rel=\"modulepreload\"; nopush, <./_app/immutable/chunks/5LFxXAy1.js>; rel=\"modulepreload\"; nopush, <./_app/immutable/nodes/0.BHDs15SW.js>; rel=\"modulepreload\"; nopush, <./_app/immutable/chunks/CExVGvqX.js>; rel=\"modulepreload\"; nopush, <./_app/immutable/chunks/DhN8On0_.js>; rel=\"modulepreload\"; nopush, <./_app/immutable/chunks/-TxsMssC.js>; rel=\"modulepreload\"; nopush, <./_app/immutable/chunks/D-pOK9nm2.js>; rel=\"modulepreload\"; nopush, <./_app/immutable/chunks/UL-13v7m.js>; rel=\"modulepreload\"; nopush, <./_app/immutable/chunks/CCOwGBqS.js>; rel=\"modulepreload\"; nopush, <./_app/immutable/chunks/BGFIlWA2.js>; rel=\"modulepreload\"; nopush, <./_app/immutable/chunks/2wmOR44T2.js>; rel=\"modulepreload\"; nopush, <./_app/immutable/chunks/DhwaxTld2.js>; rel=\"modulepreload\"; nopush, <./_app/immutable/chunks/Dhniy2Lo.js>; rel=\"modulepreload\"; nopush, <./_app/immutable/chunks/D7EXhDL8.js>; rel=\"modulepreload\"; nopush, <./_app/immutable/chunks/PCYYWU462.js>; rel=\"modulepreload\"; nopush, <./_app/immutable/chunks/DBCbViIi.js>; rel=\"modulepreload\"; nopush, <./_app/immutable/chunks/fuQEytBM.js>; rel=\"modulepreload\"; nopush, <./_app/immutable/chunks/theTV4H72.js>; rel=\"modulepreload\"; nopush, <./_app/immutable/chunks/CMweZeZB.js>; rel=\"modulepreload\"; nopush, <./_app/immutable/chunks/DX17yGJC.js>; rel=\"modulepreload\"; nopush, <./_app/immutable/chunks/CXu_Eu5i2.js>; rel=\"modulepreload\"; nopush, <./_app/immutable/chunks/Bun0zKv6.js>; rel=\"modulepreload\"; nopush, <./_app/immutable/chunks/B0cb5pph.js>; rel=\"modulepreload\"; nopush, <./_app/immutable/chunks/BrTemu3V2.js>; rel=\"modulepreload\"; nopush, <./_app/immutable/chunks/DGRmaDdp2.js>; rel=\"modulepreload\"; nopush, <./_app/immutable/chunks/gozkqann2.js>; rel=\"modulepreload\"; nopush, <./_app/immutable/chunks/BOnaymSI.js>; rel=\"modulepreload\"; nopush, <./_app/immutable/chunks/-9DdF12v.js>; rel=\"modulepreload\"; nopush, <./_app/immutable/chunks/C5BMLVxt2.js>; rel=\"modulepreload\"; nopush, <./_app/immutable/chunks/CPXIrmQo2.js>; rel=\"modulepreload\"; nopush, <./_app/immutable/chunks/BY6A6FYa2.js>; rel=\"modulepreload\"; nopush, <./_app/immutable/chunks/DuJGrVFM.js>; rel=\"modulepreload\"; nopush, <./_app/immutable/chunks/CfWZ7fZT.js>; rel=\"modulepreload\"; nopush, <./_app/immutable/chunks/7p3867yv.js>; rel=\"modulepreload\"; nopush, <./_app/immutable/chunks/h_bBM6tJ.js>; rel=\"modulepreload\"; nopush, <./_app/immutable/chunks/BDWFQU6F.js>; rel=\"modulepreload\"; nopush, <./_app/immutable/chunks/CQ-7DtNi.js>; rel=\"modulepreload\"; nopush, <./_app/immutable/chunks/D9Gfsr3u2.js>; rel=\"modulepreload\"; nopush, <./_app/immutable/chunks/Cs4dT6KT.js>; rel=\"modulepreload\"; nopush, <./_app/immutable/nodes/8.DKO0ihb1.js>; rel=\"modulepreload\"; nopush, <./_app/immutable/chunks/DA42d_oD.js>; rel=\"modulepreload\"; nopush, <./_app/immutable/chunks/_0q3g8aR.js>; rel=\"modulepreload\"; nopush, <./_app/immutable/chunks/A_GPzAoV.js>; rel=\"modulepreload\"; nopush, <./_app/immutable/chunks/DvG8pGee.js>; rel=\"modulepreload\"; nopush, <./_app/immutable/chunks/D0szcpsG.js>; rel=\"modulepreload\"; nopush, <./_app/immutable/chunks/QPtttJPU.js>; rel=\"modulepreload\"; nopush, <./_app/immutable/chunks/Bzsk5EyF2.js>; rel=\"modulepreload\"; nopush, <./_app/immutable/chunks/CMT_yxKx.js>; rel=\"modulepreload\"; nopush, <./_app/immutable/chunks/bqysOTeI.js>; rel=\"modulepreload\"; nopush, <./_app/immutable/chunks/GBGjZcmO.js>; rel=\"modulepreload\"; nopush, <./_app/immutable/chunks/DRBXT_R0.js>; rel=\"modulepreload\"; nopush, <./_app/immutable/chunks/CMH9c-If.js>; rel=\"modulepreload\"; nopush, <./_app/immutable/chunks/CkcsNjuC2.js>; rel=\"modulepreload\"; nopush, <./_app/immutable/chunks/Dp8J9ZDu.js>; rel=\"modulepreload\"; nopush, <./_app/immutable/chunks/BcgfQwqh.js>; rel=\"modulepreload\"; nopush, <./_app/immutable/chunks/DOmumyum.js>; rel=\"modulepreload\"; nopush, <./_app/immutable/chunks/BTkjfecu2.js>; rel=\"modulepreload\"; nopush, <./_app/immutable/chunks/DDIbWy8a.js>; rel=\"modulepreload\"; nopush, <./_app/immutable/chunks/3FxuDWm8.js>; rel=\"modulepreload\"; nopush, <./_app/immutable/chunks/qYBE9JkC.js>; rel=\"modulepreload\"; nopush, <./_app/immutable/chunks/BoLMZ4IX.js>; rel=\"modulepreload\"; nopush",
    "referrer-policy": "strict-origin",
    "strict-transport-security": "max-age=31536000",
    "x-content-type-options": "nosniff",
    "x-frame-options": "DENY",
    "x-request-id": "385a97ac-6991-48e5-b1f6-46cb653fb935",
    "x-sveltekit-page": "true",
    "x-xss-protection": "1; mode=block"
  },
  "endpoints": [
    {
      "hostname": "dora.inclusion.beta.gouv.fr",
      "ip": "185.21.194.105",
      "geoip": {
        "continent": {
          "code": "EU",
          "geoname_id": 6255148,
          "names": {
            "de": "Europa",
            "en": "Europe",
            "es": "Europa",
            "fr": "Europe",
            "ja": "ヨーロッパ",
            "pt-BR": "Europa",
            "ru": "Европа",
            "zh-CN": "欧洲"
          }
        },
        "country": {
          "geoname_id": 3017382,
          "is_in_european_union": true,
          "iso_code": "FR",
          "names": {
            "de": "Frankreich",
            "en": "France",
            "es": "Francia",
            "fr": "France",
            "ja": "フランス共和国",
            "pt-BR": "França",
            "ru": "Франция",
            "zh-CN": "法国"
          }
        },
        "location": {
          "accuracy_radius": 500,
          "latitude": 48.8582,
          "longitude": 2.3387,
          "time_zone": "Europe/Paris"
        },
        "registered_country": {
          "geoname_id": 3017382,
          "is_in_european_union": true,
          "iso_code": "FR",
          "names": {
            "de": "Frankreich",
            "en": "France",
            "es": "Francia",
            "fr": "France",
            "ja": "フランス共和国",
            "pt-BR": "França",
            "ru": "Франция",
            "zh-CN": "法国"
          }
        }
      }
    },
    {
      "hostname": "o4508405260615680.ingest.de.sentry.io",
      "ip": "34.160.81.0",
      "geoip": {
        "city": {
          "geoname_id": 4393217,
          "names": {
            "de": "Kansas City",
            "en": "Kansas City",
            "es": "Kansas City",
            "fr": "Kansas City",
            "ja": "カンザスシティ",
            "pt-BR": "Kansas City",
            "ru": "Канзас-Сити"
          }
        },
        "continent": {
          "code": "NA",
          "geoname_id": 6255149,
          "names": {
            "de": "Nordamerika",
            "en": "North America",
            "es": "Norteamérica",
            "fr": "Amérique du Nord",
            "ja": "北アメリカ",
            "pt-BR": "América do Norte",
            "ru": "Северная Америка",
            "zh-CN": "北美洲"
          }
        },
        "country": {
          "geoname_id": 6252001,
          "iso_code": "US",
          "names": {
            "de": "USA",
            "en": "United States",
            "es": "Estados Unidos",
            "fr": "États-Unis",
            "ja": "アメリカ",
            "pt-BR": "EUA",
            "ru": "США",
            "zh-CN": "美国"
          }
        },
        "location": {
          "accuracy_radius": 20,
          "latitude": 39.1027,
          "longitude": -94.5778,
          "metro_code": 616,
          "time_zone": "America/Chicago"
        },
        "postal": {
          "code": "64184"
        },
        "registered_country": {
          "geoname_id": 6252001,
          "iso_code": "US",
          "names": {
            "de": "USA",
            "en": "United States",
            "es": "Estados Unidos",
            "fr": "États-Unis",
            "ja": "アメリカ",
            "pt-BR": "EUA",
            "ru": "США",
            "zh-CN": "美国"
          }
        },
        "subdivisions": [
          {
            "geoname_id": 4398678,
            "iso_code": "MO",
            "names": {
              "de": "Missouri",
              "en": "Missouri",
              "es": "Missouri",
              "fr": "Missouri",
              "ja": "ミズーリ州",
              "pt-BR": "Missúri",
              "ru": "Миссури",
              "zh-CN": "密苏里州"
            }
          }
        ]
      }
    },
    {
      "hostname": "tally.so",
      "ip": "104.26.1.40",
      "geoip": {
        "registered_country": {
          "geoname_id": 6252001,
          "iso_code": "US",
          "names": {
            "de": "USA",
            "en": "United States",
            "es": "Estados Unidos",
            "fr": "États-Unis",
            "ja": "アメリカ",
            "pt-BR": "EUA",
            "ru": "США",
            "zh-CN": "美国"
          }
        }
      }
    }
  ]
}
