{
  "trackers": [],
  "cookies": [],
  "headers": {
    "alt-svc": "h3=\":443\"; ma=86400",
    "cache-control": "no-cache",
    "cf-cache-status": "DYNAMIC",
    "cf-ray": "8e3c60f22e213913-IAD",
    "content-encoding": "br",
    "content-type": "text/html; charset=utf-8",
    "date": "Sun, 17 Nov 2024 02:44:24 GMT",
    "expires": "Thu, 01 Jan 1970 00:00:01 GMT",
    "last-modified": "Tue, 05 Nov 2024 09:25:13 GMT",
    "nel": "{\"success_fraction\":0,\"report_to\":\"cf-nel\",\"max_age\":604800}",
    "report-to": "{\"endpoints\":[{\"url\":\"https:\\/\\/a.nel.cloudflare.com\\/report\\/v4?s=jsWdmCPwUlsZXitYE1so9jkUVzLyG4XuZ%2BddC7dSTR2xbPyc1u8Gb0QD0qJd0b2x8sJPzZbfZYwyJT2c6vQO1bXB8RLNlvp2yKRyXLJ6sreJOBKNH%2Bdek0zUcklE6zyBlVbFNq6nHolX\"}],\"group\":\"cf-nel\",\"max_age\":604800}",
    "server": "cloudflare",
    "server-timing": "cfL4;desc=\"?proto=TCP&rtt=5519&sent=6&recv=8&lost=0&retrans=0&sent_bytes=2857&recv_bytes=1063&delivery_rate=507552&cwnd=252&unsent_bytes=0&cid=a1b0ca858e345b61&ts=283&x=0\"",
    "vary": "Accept-Encoding"
  },
  "endpoints": [
    {
      "hostname": "cartobio.agencebio.org",
      "ip": "104.21.16.54",
      "geoip": {
        "registered_country": {
          "geoname_id": 6252001,
          "iso_code": "US",
          "names": {
            "de": "USA",
            "en": "United States",
            "es": "Estados Unidos",
            "fr": "États Unis",
            "ja": "アメリカ",
            "pt-BR": "EUA",
            "ru": "США",
            "zh-CN": "美国"
          }
        }
      }
    }
  ]
}
