{
  "trackers": [
    {
      "type": "cloudflare",
      "url": "https://static.cloudflareinsights.com/beacon.min.js/v8c78df7c7c0f484497ecbca7046644da1771523124516",
      "details": {
        "id": "cloudflare",
        "message": "Host files locally"
      }
    }
  ],
  "cookies": [],
  "headers": {
    "alt-svc": "h3=\":443\"; ma=86400",
    "cache-control": "no-cache",
    "cf-cache-status": "DYNAMIC",
    "cf-ray": "9f22a53f7f5205a0-IAD",
    "content-encoding": "zstd",
    "content-type": "text/html; charset=utf-8",
    "date": "Sun, 26 Apr 2026 03:54:19 GMT",
    "expires": "Thu, 01 Jan 1970 00:00:01 GMT",
    "last-modified": "Fri, 03 Apr 2026 11:33:20 GMT",
    "nel": "{\"report_to\":\"cf-nel\",\"success_fraction\":0.0,\"max_age\":604800}",
    "priority": "u=0,i",
    "report-to": "{\"group\":\"cf-nel\",\"max_age\":604800,\"endpoints\":[{\"url\":\"https://a.nel.cloudflare.com/report/v4?s=xoieLE%2BCvGSA1MaMbfpsmZ1l%2FS%2Fzw8DeobVZA7EMZdfZK6HZn1YfxUpVze1NDY4UW%2BWjHuLaPIQK%2FuBo%2Bz5S%2F%2FI85hauyvmx9ZOgc0Msgygv80lFVvh2%2Ba5JSbAK7ZXqaMOdDNMkKrpn\"}]}",
    "server": "cloudflare",
    "server-timing": "cfCacheStatus;desc=\"DYNAMIC\"\ncfEdge;dur=14,cfOrigin;dur=253\ncfExtPri",
    "vary": "Accept-Encoding"
  },
  "endpoints": [
    {
      "hostname": "cartobio.agencebio.org",
      "ip": "172.67.210.31",
      "geoip": {
        "registered_country": {
          "geoname_id": 6252001,
          "iso_code": "US",
          "names": {
            "de": "USA",
            "en": "United States",
            "es": "Estados Unidos",
            "fr": "États-Unis",
            "ja": "アメリカ",
            "pt-BR": "EUA",
            "ru": "США",
            "zh-CN": "美国"
          }
        }
      }
    },
    {
      "hostname": "static.cloudflareinsights.com",
      "ip": "104.16.80.73",
      "geoip": {
        "registered_country": {
          "geoname_id": 6252001,
          "iso_code": "US",
          "names": {
            "de": "USA",
            "en": "United States",
            "es": "Estados Unidos",
            "fr": "États-Unis",
            "ja": "アメリカ",
            "pt-BR": "EUA",
            "ru": "США",
            "zh-CN": "美国"
          }
        }
      }
    }
  ]
}
