{"token":"803w","url":"https://deveco.incubateur.anct.gouv.fr","alias":null,"last_status":200,"uptime":99.112,"down":false,"down_since":null,"up_since":"2025-01-11T12:34:39Z","error":null,"period":60,"apdex_t":0.5,"string_match":"","enabled":true,"published":true,"disabled_locations":[],"recipients":["slack_compatible:4124784183"],"last_check_at":"2025-01-12T03:01:39Z","next_check_at":"2025-01-12T03:02:39Z","created_at":"2024-01-15T13:56:21Z","mute_until":null,"favicon_url":"https://deveco.incubateur.anct.gouv.fr/dsfr/favicon/favicon.ico","custom_headers":{},"http_verb":"GET/HEAD","http_body":"","ssl":{"tested_at":"2025-01-12T02:57:41Z","expires_at":"2025-03-14T10:15:03Z","valid":true,"error":null},"metrics":{"apdex":0.992,"timings":{"redirect":0,"namelookup":328,"connection":134,"handshake":172,"response":158,"total":792}},"uptimeGrade":"A","apdexGrade":"A"}