[
         {
              "id"           : "scanProblem",
              "ip"           : "futurpro.inserjeunes.beta.gouv.fr/54.38.224.97",
              "port"         : "443",
              "severity"     : "FATAL",
              "finding"      : "Can't connect to '54.38.224.97:443' Make sure a firewall is not between you and your scanning target!"
          }
,         {
              "id"           : "scanTime",
              "ip"           : "futurpro.inserjeunes.beta.gouv.fr/54.38.224.97",
              "port"         : "443",
              "severity"     : "WARN",
              "finding"      : "Scan interrupted"
          }
]
