{"token":"thda","url":"https://app.datasubvention.beta.gouv.fr","type":"https","alias":null,"uptime":99.67,"down":false,"down_since":null,"up_since":"2025-08-09T11:37:31Z","error":null,"period":60,"string_match":"","enabled":true,"published":true,"recipients":["slack_compatible:925164844"],"last_check_at":"2025-08-10T10:50:57Z","next_check_at":"2025-08-10T10:51:57Z","created_at":"2024-01-15T14:01:08Z","mute_until":null,"last_status":200,"apdex_t":0.5,"disabled_locations":[],"custom_headers":{},"favicon_url":"https://app.datasubvention.beta.gouv.fr/dsfr/favicon.ico","http_verb":"GET/HEAD","http_body":"","ssl":{"tested_at":"2025-08-10T10:50:00Z","expires_at":"2025-09-18T08:14:43Z","valid":true,"error":null},"metrics":{"apdex":1,"timings":{"redirect":0,"namelookup":108,"connection":136,"handshake":140,"response":141,"total":525}},"uptimeGrade":"A","apdexGrade":"A"}