{
  "scan": {
    "algorithmVersion": 4,
    "grade": "B-",
    "error": null,
    "score": 65,
    "statusCode": 200,
    "testsFailed": 3,
    "testsPassed": 7,
    "testsQuantity": 10,
    "responseHeaders": {
      "connection": "close",
      "cache-control": "max-age=0, private, must-revalidate",
      "content-type": "text/html; charset=utf-8",
      "etag": "W/\"a5b3e6b69b80d40f8b55eafe1cd71467\"",
      "link": "</assets/application-881d1f62c4e68645c4a0d4125f0ee3c43f8d434723925d7adb65fd63a71e3ec2.css>; rel=preload; as=style; nopush",
      "referrer-policy": "strict-origin-when-cross-origin",
      "set-cookie": [
        "_ellesfontlaphoto_session=9%2Bm8F%2F%2F8IdWojKu9FHmGWnsp2PKbd3i2bjRz7X4cgaWCMll0U7pF5%2FgzT%2FngXqfbValXKJbIjvqAwnsKhJMnDQekODXzwTr3dSTlGl6dVMatphCHzpI80ZW3slqlIP%2FooyFjeohFNXSRVDA9ij7FCxRtUZj1kMjF7Q24sRSGcsd%2FfiaJN6h%2FGBmpIoB4egURNlhAXNx1NT98YdwPU1sORDttNHZwIvZvGTO7aace3YcO3avF3V8ofwYEy2adKmYlRmJwECv4SqHVUdj4vaM%2BqYp6Meuqpr2N1i26mMm34pVZfoKJSw2az72DOaRUQ7OF3HM6qi%2BRPSoeZRaBqAx1zsX2Fh6Oy4ygbbDQdkWWfjcbJXGqUsZonD6q0e72f2VeA3Vw0i3YpctjtpKzSe7HIO8X0aZsEnfPjycU0gyu4zWk%2FFypqyEbuSglzP1FaUSPVTolja6rJVG0G1YNnUNoCk48PrMTlz9%2Bs8X9bJINda4L1uDEB2IgumB0QxzzDzMqpg%3D%3D--T%2BOHVw5ALyp6Vutr--5p1uO4x6AetRfDFqE0upAw%3D%3D; path=/; secure; HttpOnly; SameSite=Lax"
      ],
      "traceresponse": "00-1837f900a110ed58ecdd91cacaa9bd7b-3acbbcc131b92710-01",
      "x-content-type-options": "nosniff",
      "x-debug-info": "eyJyZXRyaWVzIjowfQ==",
      "x-download-options": "noopen",
      "x-frame-options": "SAMEORIGIN",
      "x-permitted-cross-domain-policies": "none",
      "x-platform-cache": "MISS",
      "x-platform-cluster": "tl34jw4qs4bu2-master-7rqtwti",
      "x-platform-processor": "gwzrtyfmq5bg3qickflrztm5jm",
      "x-platform-router": "nthylk4d6puxch5isukqy3sywa",
      "x-request-id": "495a365c-613a-43c3-beaf-3cd4d76adc3c",
      "x-runtime": "0.321480",
      "x-xss-protection": "1; mode=block",
      "accept-ranges": "bytes",
      "via": "1.1 varnish, 1.1 varnish",
      "date": "Sun, 20 Apr 2025 08:19:22 GMT",
      "x-served-by": "cache-par-lfpg1960062-PAR, cache-iad-kcgs7200099-IAD",
      "x-cache": "MISS, MISS",
      "x-cache-hits": "0, 0",
      "strict-transport-security": "max-age=31557600",
      "transfer-encoding": "chunked"
    }
  },
  "tests": {
    "content-security-policy": {
      "expectation": "csp-implemented-with-no-unsafe",
      "pass": false,
      "result": "csp-not-implemented",
      "scoreModifier": -25,
      "data": null,
      "http": false,
      "meta": false,
      "policy": null,
      "numPolicies": 0
    },
    "cookies": {
      "expectation": "cookies-secure-with-httponly-sessions",
      "pass": true,
      "result": "cookies-secure-with-httponly-sessions-and-samesite",
      "scoreModifier": 5,
      "data": {
        "_ellesfontlaphoto_session": {
          "domain": "ellesfontla.culture.gouv.fr",
          "httponly": true,
          "path": "/",
          "port": null,
          "samesite": "lax",
          "secure": true
        }
      },
      "sameSite": true
    },
    "cross-origin-resource-sharing": {
      "expectation": "cross-origin-resource-sharing-not-implemented",
      "pass": true,
      "result": "cross-origin-resource-sharing-not-implemented",
      "scoreModifier": 0,
      "data": null
    },
    "redirection": {
      "expectation": "redirection-to-https",
      "pass": false,
      "result": "redirection-off-host-from-http",
      "scoreModifier": -5,
      "destination": "https://ellesfontla.culture.gouv.fr/",
      "redirects": true,
      "route": [
        "http://ellesfontlaculture.beta.gouv.fr/",
        "https://ellesfontla.culture.gouv.fr/"
      ],
      "statusCode": 200
    },
    "referrer-policy": {
      "expectation": "referrer-policy-private",
      "pass": true,
      "result": "referrer-policy-private",
      "scoreModifier": 5,
      "data": "strict-origin-when-cross-origin",
      "http": true,
      "meta": false
    },
    "strict-transport-security": {
      "expectation": "hsts-implemented-max-age-at-least-six-months",
      "pass": true,
      "result": "hsts-implemented-max-age-at-least-six-months",
      "scoreModifier": 0,
      "data": "max-age=31557600",
      "includeSubDomains": false,
      "maxAge": 31557600,
      "preload": false,
      "preloaded": false
    },
    "subresource-integrity": {
      "expectation": "sri-implemented-and-external-scripts-loaded-securely",
      "pass": false,
      "result": "sri-not-implemented-but-external-scripts-loaded-securely",
      "scoreModifier": -5,
      "data": {
        "https://cdnjs.cloudflare.com/ajax/libs/tarteaucitronjs/1.13.0/tarteaucitron.js": {
          "crossorigin": null,
          "integrity": null
        }
      }
    },
    "x-content-type-options": {
      "expectation": "x-content-type-options-nosniff",
      "pass": true,
      "result": "x-content-type-options-nosniff",
      "scoreModifier": 0,
      "data": "nosniff"
    },
    "x-frame-options": {
      "expectation": "x-frame-options-sameorigin-or-deny",
      "pass": true,
      "result": "x-frame-options-sameorigin-or-deny",
      "scoreModifier": 0,
      "data": "SAMEORIGIN"
    },
    "cross-origin-resource-policy": {
      "expectation": "corp-implemented-with-same-site",
      "pass": true,
      "result": "corp-not-implemented",
      "scoreModifier": 0,
      "data": null,
      "http": false,
      "meta": false
    }
  }
}
