{
  "trackers": [
    {
      "type": "cloudflare",
      "url": "https://cdnjs.cloudflare.com/ajax/libs/tarteaucitronjs/1.13.0/tarteaucitron.js",
      "details": {
        "id": "cloudflare",
        "message": "Host files locally"
      }
    }
  ],
  "cookies": [
    {
      "name": "_ellesfontlaphoto_session",
      "value": "08UZqhr0M0Lk4nDH3nkFR1XGVVRqqpfMvzl385t7lw%2Fh7mTlpFXVk9nBowz3KTkY7vFdMGlajlN8j1IthC3Tlvixv%2Btc7rHGh8NHiM95CPm2i4db03s80pZIjf1Dqb%2Fc7ZmJFgUVxZlsjugDiGSN%2B3BHS%2Fh1al8B9rZY6RcBkqme1Z7RxWp%2B7uO9tSojY%2FqwpY6QdWP8Jq9NWNq9TfBRSy%2F0xsTs9zm0buG%2BXEkgmGVJeXyHSqFmQ9LzsLOJwCqHDRmOygthn6rsY29%2BjS%2Bwk%2FlMk5BKAJFK2W%2BCoNoI9sbOItxcts0NnYO03zHEM1wO7eBQ013iObJafrA8xqUVfIsMibvQk%2FWwD5ZDlV3JJLUXw4pLNUPZC03XsN%2FDo2fRPEEKn22J0mTWumXZry40p%2BXZmUBsFer5Cx15Gb7GIbGK6xo6rA5mAxpQ5dPLzRLITbmcX6Nci%2BDlI3rq7taB9sptRZjHhWwbbS%2FXK%2FBd%2FKGw8AJU%2BnZIdCpXwX3whaSCzA%3D%3D--yKhuf%2BReSYKcj16s--I5RJx6HcCQMAIs77xJaaeQ%3D%3D",
      "domain": "ellesfontla.culture.gouv.fr",
      "path": "/",
      "expires": -1,
      "size": 637,
      "httpOnly": true,
      "secure": true,
      "session": true,
      "sameSite": "Lax",
      "priority": "Medium",
      "sameParty": false,
      "sourceScheme": "Secure"
    },
    {
      "name": "_pk_ses.187.1dd6",
      "value": "1",
      "domain": "ellesfontla.culture.gouv.fr",
      "path": "/",
      "expires": 1763285801,
      "size": 17,
      "httpOnly": false,
      "secure": false,
      "session": false,
      "sameSite": "Lax",
      "priority": "Medium",
      "sameParty": false,
      "sourceScheme": "Secure"
    },
    {
      "name": "_pk_id.187.1dd6",
      "value": "ed62c54ad9bfaae4.1763284001.",
      "domain": "ellesfontla.culture.gouv.fr",
      "path": "/",
      "expires": 1797239201,
      "size": 43,
      "httpOnly": false,
      "secure": false,
      "session": false,
      "sameSite": "Lax",
      "priority": "Medium",
      "sameParty": false,
      "sourceScheme": "Secure"
    }
  ],
  "headers": {
    "accept-ranges": "bytes",
    "cache-control": "max-age=0, private, must-revalidate",
    "content-type": "text/html; charset=utf-8",
    "date": "Sun, 16 Nov 2025 09:06:40 GMT",
    "etag": "W/\"23c16b13850a5149e537643de4fe6321\"",
    "link": "</assets/application-7cdfed0474f21f63530b7039ece3ebb034f01d06b7f745f0ed4f0d98a533ba57.css>; rel=preload; as=style; nopush",
    "referrer-policy": "strict-origin-when-cross-origin",
    "set-cookie": "_ellesfontlaphoto_session=bTV5jlyHSjVFk8KpZslJWqcqq0jr9KwMuU5ouIZHuvmmc%2F9gQdUl%2FMbIH2kGJAOAIAT0VrYPX1c%2B9IhOvFqsgUjb9BRq8hTVa1Sce163wXiBwj1wODamDVcvh69owWa4lJjQXOswn4zZqx2NBJAw%2BEZwxtA3kiftQi1EVwLD1%2F7KFyVKHu0G3jZdvcXTKLTCVvmPineuaAUUE9Gn63Gis%2FNV9wWUt6VOV66RMz8Uey4aj7X5SQ8Z3VLvbGgDgoypJpkC5MxkUZ7SQbuyig8lj8HjNSy0tgD7TuDBaqnd18%2FTtonZ2YQglojXekK0p%2F96DqDrlSvbgYuDOFmRzfrsiqoI5RglcFQNMjTuRngDr57xUqgZzS%2B%2BtFFvNQjoSfGuJ29X8yR%2FDt6kkfuEASwYegyw5ybjIs93A3R8PQ3DgzF5QTelIOP7lz6mwippPz%2FHDBd%2BWzhp6RyZry1Uwu57SeXaIgXtVUyFAzQyDNLEFEBDpCzaaSM1KmzyF03dEOWNaw%3D%3D--ovjTMC1abEpX1b%2F1--2jUNleIBAJorhLdyrcXB8A%3D%3D; path=/; secure; HttpOnly; SameSite=Lax",
    "strict-transport-security": "max-age=31557600",
    "traceresponse": "00-18787174d0acc70202c212d5b5b627e4-4e0a3f8a122ad328-01",
    "via": "1.1 varnish, 1.1 varnish",
    "x-cache": "MISS, MISS",
    "x-cache-hits": "0, 0",
    "x-content-type-options": "nosniff",
    "x-debug-info": "eyJyZXRyaWVzIjowfQ==",
    "x-download-options": "noopen",
    "x-frame-options": "SAMEORIGIN",
    "x-permitted-cross-domain-policies": "none",
    "x-platform-cache": "MISS",
    "x-platform-cluster": "tl34jw4qs4bu2-master-7rqtwti",
    "x-platform-processor": "gwzrtyfmq5bg3qickflrztm5jm",
    "x-platform-router": "nthylk4d6puxch5isukqy3sywa",
    "x-request-id": "12415a3b-6b72-4cb4-94f3-0cdaa53d97e1",
    "x-runtime": "0.198345",
    "x-served-by": "cache-par-lfpb1150046-PAR, cache-iad-kiad7000045-IAD",
    "x-xss-protection": "1; mode=block"
  },
  "endpoints": [
    {
      "hostname": "ellesfontlaculture.beta.gouv.fr",
      "ip": "185.31.40.17",
      "geoip": {
        "continent": {
          "code": "EU",
          "geoname_id": 6255148,
          "names": {
            "de": "Europa",
            "en": "Europe",
            "es": "Europa",
            "fr": "Europe",
            "ja": "ヨーロッパ",
            "pt-BR": "Europa",
            "ru": "Европа",
            "zh-CN": "欧洲"
          }
        },
        "country": {
          "geoname_id": 3017382,
          "is_in_european_union": true,
          "iso_code": "FR",
          "names": {
            "de": "Frankreich",
            "en": "France",
            "es": "Francia",
            "fr": "France",
            "ja": "フランス共和国",
            "pt-BR": "França",
            "ru": "Франция",
            "zh-CN": "法国"
          }
        },
        "location": {
          "accuracy_radius": 500,
          "latitude": 48.8582,
          "longitude": 2.3387,
          "time_zone": "Europe/Paris"
        },
        "registered_country": {
          "geoname_id": 3017382,
          "is_in_european_union": true,
          "iso_code": "FR",
          "names": {
            "de": "Frankreich",
            "en": "France",
            "es": "Francia",
            "fr": "France",
            "ja": "フランス共和国",
            "pt-BR": "França",
            "ru": "Франция",
            "zh-CN": "法国"
          }
        }
      }
    },
    {
      "hostname": "cdnjs.cloudflare.com",
      "ip": "104.17.24.14",
      "geoip": {
        "registered_country": {
          "geoname_id": 6252001,
          "iso_code": "US",
          "names": {
            "de": "USA",
            "en": "United States",
            "es": "Estados Unidos",
            "fr": "États Unis",
            "ja": "アメリカ",
            "pt-BR": "EUA",
            "ru": "США",
            "zh-CN": "美国"
          }
        }
      }
    }
  ]
}
