{"token":"1jnj","url":"https://mesaidesreno.beta.gouv.fr","alias":null,"last_status":200,"uptime":100,"down":false,"down_since":null,"up_since":"2025-01-23T12:55:26Z","error":null,"period":60,"apdex_t":0.5,"string_match":"","enabled":true,"published":true,"disabled_locations":[],"recipients":["email:3896582286","slack_compatible:4124784183"],"last_check_at":"2025-01-26T14:24:34Z","next_check_at":"2025-01-26T14:25:34Z","created_at":"2024-12-01T01:53:41Z","mute_until":null,"favicon_url":null,"custom_headers":{},"http_verb":"GET/HEAD","http_body":"","ssl":{"tested_at":"2025-01-26T14:17:37Z","expires_at":"2025-03-10T15:48:38Z","valid":true,"error":null},"metrics":{"apdex":1,"timings":{"redirect":0,"namelookup":153,"connection":112,"handshake":118,"response":116,"total":498}},"uptimeGrade":"A","apdexGrade":"A"}