{
  "id": "jafer",
  "type": "startup",
  "attributes": {
    "name": "JAFER",
    "pitch": "Diminuer les délais de prise en charge, par les espaces de rencontre, des mesures judiciaires ordonnant des visites parent/enfant ",
    "stats_url": "https://jafer.beta.gouv.fr/chiffres-cles",
    "budget_url": "https://pad.numerique.gouv.fr/s/WYougVwWu#JAFER",
    "impact_url": "",
    "link": "https://jafer.beta.gouv.fr/",
    "contact": "jafer.sadjav-sg@justice.gouv.fr",
    "content_url_encoded_markdown": "%23%23%20Contexte%0A%0AUn%20espace%20de%20rencontre%20est%20un%20lieu%20%C2%AB%20neutre%20%C2%BB%20permettant%20%C3%A0%20un%20enfant%20confi%C3%A9%20%C3%A0%20un%20parent%20de%20rencontrer%20l%E2%80%99autre%20parent%20dans%20des%20conditions%20permettant%20de%20favoriser%20la%20reprise%20du%20lien%20tout%20en%20assurant%20la%20s%C3%A9curit%C3%A9%20physique%20et%20psychique%20de%20l%E2%80%99enfant%20et%20des%20parents.%20Il%20existe%20192%20espaces%20de%20rencontre.%20%20En%202021%2C%20pr%C3%A8s%20de%2030%20000%20enfants%20ont%20%C3%A9t%C3%A9%20accueillis%20dans%20un%20espace%20de%20rencontre%2C%20dont%2090%25%20suite%20%C3%A0%20l%E2%80%99ordonnance%20d%E2%80%99un%20juge%20aux%20affaires%20familiales.%20%20%20Les%20d%C3%A9lais%20de%20prise%20en%20charge%20d%E2%80%99une%20mesure%20sont%20actuellement%20trop%20importants%20et%20peuvent%20aggraver%20les%20situations%20de%20ruptures%20familiales.%20%20Comment%20mieux%20r%C3%A9partir%20la%20charge%20de%20travail%20des%20espaces%20de%20rencontre%20et%20diminuer%20les%20d%C3%A9lais%20de%20prise%20en%20charge%20des%20mesures%20afin%20de%20rendre%20un%20meilleur%20service%20aux%20familles%20%3F%0A%0A%23%23%20Probl%C3%A8me%0A%0ALes%20d%C3%A9lais%20de%20prise%20en%20charge%20d%E2%80%99une%20mesure%20sont%20actuellement%20trop%20importants%20et%20peuvent%20aggraver%20les%20situations%20de%20ruptures%20familiales.%20Comment%20mieux%20r%C3%A9partir%20la%20charge%20de%20travail%20des%20espaces%20de%20rencontre%20et%20diminuer%20les%20d%C3%A9lais%20de%20prise%20en%20charge%20des%20mesures%20afin%20de%20rendre%20un%20meilleur%20service%20aux%20familles%20%3F%20Par%20ailleurs%2C%20au%20moment%20de%20d%C3%A9signer%20un%20espace%20de%20rencontre%2C%20les%20juges%20aux%20affaires%20familiales%20ne%20connaissent%20pas%20pr%C3%A9cis%C3%A9ment%20la%20dur%C3%A9e%20d%E2%80%99attente%20ni%20les%20modalit%C3%A9s%20d%E2%80%99accueil%20des%20diff%C3%A9rentes%20structures%20existantes.%20%0A%0A%23%23%20Solution%0A%0AAfin%20de%20favoriser%20la%20connaissance%20des%20modalit%C3%A9s%20d%E2%80%99accueil%20au%20sein%20des%20espaces%20de%20rencontre%20par%20les%20juges%20aux%20affaires%20familiales%2C%20nous%20proposons%20la%20mise%20en%20place%20d%E2%80%99un%20outil%20de%20suivi%20des%20d%C3%A9lais%20d%E2%80%99attente%20et%20des%20modalit%C3%A9s%20particuli%C3%A8res%20d%E2%80%99accueil.%0A%0A%23%23%20Strat%C3%A9gie%0A%0A%2A%20%C3%89tendre%20la%20couverture%20g%C3%A9ographique%20%C3%A0%20l%27%C3%A9chelle%20nationale.%20%0A%0A%2A%20Enrichir%20fonctionnellement%20le%20produit%20%3A%20%0A%2A%20Permettre%20aux%20JAFs%20de%20compl%C3%A9ter%20une%20mesure%20et%20la%20transmettre%20aux%20espaces%20de%20rencontres%2C%20%0A%2A%20Am%C3%A9liorer%20la%20communication%20entre%20juges%20et%20espaces%20de%20rencontre%20via%20notamment%20une%20messagerie%20interne%2C%20%0A%2A%20Permettre%20aux%20espaces%20de%20rencontre%20de%20g%C3%A9rer%20leur%20espace%20%C3%A0%20plusieurs%20contacts.%0A",
    "events": [],
    "phases": [
      {
        "name": "investigation",
        "start": "2022-06-29",
        "end": "2022-12-06"
      },
      {
        "name": "construction",
        "start": "2022-12-07",
        "end": ""
      },
      {
        "name": "acceleration",
        "start": "2025-01-02",
        "end": ""
      }
    ],
    "sponsors": [
      "mj"
    ],
    "thematiques": [
      "Justice"
    ],
    "technos": [],
    "dashlord_url": "https://dashlord.incubateur.net/url/jafer-beta-gouv-fr/best-practices/",
    "accessibility_status": "partiellement conforme"
  },
  "relationships": {
    "incubator": {
      "data": {
        "type": "incubator",
        "id": "justice"
      }
    }
  }
}
